orcheo_sdk/__init__.py
orcheo_sdk/py.typed
orcheo_sdk/workflow.py
orcheo_sdk/cli/__init__.py
orcheo_sdk/cli/agent_tool.py
orcheo_sdk/cli/cache.py
orcheo_sdk/cli/codegen.py
orcheo_sdk/cli/config.py
orcheo_sdk/cli/config_command.py
orcheo_sdk/cli/credential.py
orcheo_sdk/cli/edge.py
orcheo_sdk/cli/errors.py
orcheo_sdk/cli/http.py
orcheo_sdk/cli/main.py
orcheo_sdk/cli/node.py
orcheo_sdk/cli/output.py
orcheo_sdk/cli/service_token.py
orcheo_sdk/cli/state.py
orcheo_sdk/cli/utils.py
orcheo_sdk/cli/auth/__init__.py
orcheo_sdk/cli/auth/commands.py
orcheo_sdk/cli/auth/config.py
orcheo_sdk/cli/auth/oauth.py
orcheo_sdk/cli/auth/refresh.py
orcheo_sdk/cli/auth/tokens.py
orcheo_sdk/cli/workflow/__init__.py
orcheo_sdk/cli/workflow/app.py
orcheo_sdk/cli/workflow/formatting.py
orcheo_sdk/cli/workflow/ingest.py
orcheo_sdk/cli/workflow/inputs.py
orcheo_sdk/cli/workflow/mermaid.py
orcheo_sdk/cli/workflow/streaming.py
orcheo_sdk/cli/workflow/commands/__init__.py
orcheo_sdk/cli/workflow/commands/listing.py
orcheo_sdk/cli/workflow/commands/managing.py
orcheo_sdk/cli/workflow/commands/publishing.py
orcheo_sdk/cli/workflow/commands/running.py
orcheo_sdk/cli/workflow/commands/scheduling.py
orcheo_sdk/cli/workflow/commands/showing.py
orcheo_sdk/client/__init__.py
orcheo_sdk/client/executor.py
orcheo_sdk/client/orcheo_client.py
orcheo_sdk/mcp_server/__init__.py
orcheo_sdk/mcp_server/agent_tool_bindings.py
orcheo_sdk/mcp_server/codegen_tools.py
orcheo_sdk/mcp_server/config.py
orcheo_sdk/mcp_server/credential_tools.py
orcheo_sdk/mcp_server/edge_tools.py
orcheo_sdk/mcp_server/main.py
orcheo_sdk/mcp_server/node_tools.py
orcheo_sdk/mcp_server/server.py
orcheo_sdk/mcp_server/service_token_tools.py
orcheo_sdk/mcp_server/workflow_tools.py
orcheo_sdk/mcp_server/tools/__init__.py
orcheo_sdk/mcp_server/tools/agent_tools.py
orcheo_sdk/mcp_server/tools/codegen.py
orcheo_sdk/mcp_server/tools/credentials.py
orcheo_sdk/mcp_server/tools/edges.py
orcheo_sdk/mcp_server/tools/nodes.py
orcheo_sdk-0.14.0.dist-info/METADATA
orcheo_sdk-0.14.0.dist-info/WHEEL
orcheo_sdk-0.14.0.dist-info/entry_points.txt
orcheo_sdk-0.14.0.dist-info/RECORD
