Metadata-Version: 2.4
Name: orcheo-sdk
Version: 0.14.0
Summary: Client helpers for the Orcheo workflow orchestration platform
Requires-Python: >=3.12
Requires-Dist: fastmcp>=2.13.0.2
Requires-Dist: httpx>=0.27.0
Requires-Dist: orcheo>=0.18.0
Requires-Dist: rich>=13.7.0
Requires-Dist: typer>=0.12.3
Provides-Extra: dev
Requires-Dist: mypy; extra == 'dev'
Requires-Dist: pytest; extra == 'dev'
Requires-Dist: pytest-cov; extra == 'dev'
Requires-Dist: respx>=0.21.0; extra == 'dev'
Requires-Dist: ruff; extra == 'dev'
